markpact/__init__.py
markpact/auto_fix.py
markpact/cli.py
markpact/config.py
markpact/converter.py
markpact/docker_runner.py
markpact/generator.py
markpact/notebook_converter.py
markpact/parser.py
markpact/publisher.py
markpact/runner.py
markpact/sandbox.py
markpact/tester.py
markpact-0.1.16.dist-info/METADATA
markpact-0.1.16.dist-info/WHEEL
markpact-0.1.16.dist-info/entry_points.txt
markpact-0.1.16.dist-info/licenses/LICENSE
markpact-0.1.16.dist-info/RECORD
