Metadata-Version: 2.4
Name: markpact
Version: 0.1.16
Summary: Executable Markdown Runtime – run projects from README.md
Project-URL: Homepage, https://github.com/wronai/markpact
Project-URL: Repository, https://github.com/wronai/markpact
Project-URL: Issues, https://github.com/wronai/markpact/issues
Author: wronai
License-Expression: Apache-2.0
License-File: LICENSE
Keywords: executable,markdown,readme,runtime,sandbox
Classifier: Development Status :: 3 - Alpha
Classifier: Environment :: Console
Classifier: Intended Audience :: Developers
Classifier: License :: OSI Approved :: Apache Software License
Classifier: Programming Language :: Python :: 3
Classifier: Programming Language :: Python :: 3.10
Classifier: Programming Language :: Python :: 3.11
Classifier: Programming Language :: Python :: 3.12
Classifier: Programming Language :: Python :: 3.13
Classifier: Topic :: Software Development :: Build Tools
Classifier: Topic :: Text Processing :: Markup :: Markdown
Requires-Python: >=3.10
Provides-Extra: dev
Requires-Dist: build; extra == 'dev'
Requires-Dist: bump2version>=1.0; extra == 'dev'
Requires-Dist: litellm>=1.0; extra == 'dev'
Requires-Dist: pytest-cov>=4.0; extra == 'dev'
Requires-Dist: pytest>=7.0; extra == 'dev'
Requires-Dist: ruff>=0.1; extra == 'dev'
Requires-Dist: twine; extra == 'dev'
Provides-Extra: llm
Requires-Dist: litellm>=1.0; extra == 'llm'
